setup.cfg
setup.py
test/test.py
walkscore/__init__.py
walkscore/api.py
walkscore_api_binding.egg-info/PKG-INFO
walkscore_api_binding.egg-info/SOURCES.txt
walkscore_api_binding.egg-info/dependency_links.txt
walkscore_api_binding.egg-info/top_level.txt