Metadata-Version: 1.1
Name: walkscore-api-binding
Version: 0.2.2
Summary: Unofficial WalkScore API binding
Home-page: https://github.com/knockrentals/walkscore
Author: Jay Zeng
Author-email: jayzeng@jay-zeng.com
License: UNKNOWN
Download-URL: https://github.com/knockrentals/walkscore/releases/tag/0.2.2
Keywords: walkscore,api,binding
Platform: UNKNOWN
Classifier: Development Status :: 5 - Production/Stable
Classifier: Intended Audience :: Developers
Classifier: License :: OSI Approved :: MIT License
Classifier: Operating System :: OS Independent
Classifier: Programming Language :: Python
Classifier: Topic :: Scientific/Engineering :: GIS
Classifier: Topic :: Software Development :: Libraries :: Python Modules
Classifier: Programming Language :: Python :: 2
Classifier: Programming Language :: Python :: 3
